lfsr_crc_project/crc8_generator.sv
`timescale 1ns/1ps

module crc8_generator (
    input  logic       clk,
    input  logic       rst,
    input  logic       start,
    input  logic [7:0] data_in,

    output logic [7:0] crc_out,
    output logic       done
);

    logic [7:0] crc_reg;
    logic [2:0] bit_count;
    logic       busy;
    logic       feedback;

    // Feedback = CRC MSB XOR current input bit
    assign feedback = crc_reg[7] ^ data_in[7-bit_count];

    always_ff @(posedge clk or posedge rst) begin

        if (rst) begin

            crc_reg  <= 8'h00;
            crc_out  <= 8'h00;
            bit_count <= 3'd0;
            busy     <= 1'b0;
            done     <= 1'b0;

        end

        else begin

            // DONE is normally low
            done <= 1'b0;

            // Start CRC calculation
            if (start && !busy) begin

                crc_reg   <= 8'h00;
                bit_count <= 3'd0;
                busy      <= 1'b1;

            end

            // CRC calculation
            else if (busy) begin

                if (feedback)
                    crc_reg <= {crc_reg[6:0], 1'b0} ^ 8'h07;
                else
                    crc_reg <= {crc_reg[6:0], 1'b0};

                // Last input bit
                if (bit_count == 3'd7) begin

                    crc_out <= feedback ?
                               ({crc_reg[6:0], 1'b0} ^ 8'h07) :
                               ({crc_reg[6:0], 1'b0});

                    done <= 1'b1;
                    busy <= 1'b0;

                end

                else begin

                    bit_count <= bit_count + 1'b1;

                end

            end

        end

    end

endmodule

lfsr_crc_project/tb_crc8.sv
`timescale 1ns/1ps

module tb_crc8;

    logic       clk;
    logic       rst;
    logic       start;
    logic [7:0] data_in;

    logic [7:0] crc_out;
    logic       done;


    //================================================
    // DUT
    //================================================

    crc8_generator DUT (
        .clk     (clk),
        .rst     (rst),
        .start   (start),
        .data_in (data_in),
        .crc_out (crc_out),
        .done    (done)
    );


    //================================================
    // CLOCK GENERATION
    //================================================

    initial begin

        clk = 1'b0;

        forever #5 clk = ~clk;

    end


    //================================================
    // VCD WAVEFORM
    //================================================

    initial begin

        $dumpfile("crc8_waveform.vcd");
        $dumpvars(0, tb_crc8);

    end


    //================================================
    // TEST SEQUENCE
    //================================================

    initial begin

        // Initial values
        rst     = 1'b1;
        start   = 1'b0;
        data_in = 8'h00;

        // Reset
        #20;

        rst = 1'b0;


        //================================================
        // TEST 1 : A5
        //================================================

        data_in = 8'hA5;

        #10;

        start = 1'b1;

        #10;

        start = 1'b0;

        wait(done == 1'b1);

        #1;

        $display("-----------------------------------------------");
        $display("TEST 1");
        $display("Input Data : %h", data_in);
        $display("CRC Output : %h", crc_out);
        $display("DONE       : %b", done);
        $display("-----------------------------------------------");


        //================================================
        // TEST 2 : 3C
        //================================================

        #20;

        data_in = 8'h3C;

        #10;

        start = 1'b1;

        #10;

        start = 1'b0;

        wait(done == 1'b1);

        #1;

        $display("-----------------------------------------------");
        $display("TEST 2");
        $display("Input Data : %h", data_in);
        $display("CRC Output : %h", crc_out);
        $display("DONE       : %b", done);
        $display("-----------------------------------------------");


        #20;

        $display("Simulation completed.");

        $finish;

    end

endmodule

lfsr_crc_project/crc8_waveform.vcd
$version Generated by VerilatedVcd $end
$timescale 1ps $end
 $scope module tb_crc8 $end
  $var wire 1 ' clk $end
  $var wire 1 ( rst $end
  $var wire 1 ) start $end
  $var wire 8 * data_in [7:0] $end
  $var wire 8 " crc_out [7:0] $end
  $var wire 1 # done $end
  $scope module DUT $end
   $var wire 1 ' clk $end
   $var wire 1 ( rst $end
   $var wire 1 ) start $end
   $var wire 8 * data_in [7:0] $end
   $var wire 8 " crc_out [7:0] $end
   $var wire 1 # done $end
   $var wire 8 $ crc_reg [7:0] $end
   $var wire 3 % bit_count [2:0] $end
   $var wire 1 & busy $end
   $var wire 1 + feedback $end
  $upscope $end
 $upscope $end
$enddefinitions $end


#0
b00000000 "
0#
b00000000 $
b000 %
0&
0'
1(
0)
b00000000 *
0+
#5000
1'
#10000
0'
#15000
1'
#20000
0'
0(
b10100101 *
1+
#25000
1'
#30000
0'
1)
#35000
1&
1'
#40000
0'
0)
#45000
b00000111 $
b001 %
1'
0+
#50000
0'
#55000
b00001110 $
b010 %
1'
1+
#60000
0'
#65000
b00011011 $
b011 %
1'
0+
#70000
0'
#75000
b00110110 $
b100 %
1'
#80000
0'
#85000
b01101100 $
b101 %
1'
1+
#90000
0'
#95000
b11011111 $
b110 %
1'
#100000
0'
#105000
b10111001 $
b111 %
1'
0+
#110000
0'
#115000
b01110010 "
1#
b01110010 $
0&
1'
1+
#120000
0'
#125000
0#
1'
#130000
0'
#135000
1'
#136000
b00111100 *
0+
#140000
0'
#145000
1'
#146000
1)
#150000
0'
#155000
b00000000 $
b000 %
1&
1'
#156000
0)
#160000
0'
#165000
b001 %
1'
#170000
0'
#175000
b010 %
1'
1+
#180000
0'
#185000
b00000111 $
b011 %
1'
#190000
0'
#195000
b00001001 $
b100 %
1'
#200000
0'
#205000
b00010101 $
b101 %
1'
#210000
0'
#215000
b00101101 $
b110 %
1'
0+
#220000
0'
#225000
b01011010 $
b111 %
1'
#230000
0'
#235000
b10110100 "
1#
b10110100 $
0&
1'
1+
#240000
0'
#245000
0#
1'
